<?xml version="1.0" encoding="UTF-8"?>
<profile>
    <name>Boomi</name>
    <language>xml</language>
    <rules>
        <rule>
            <repositoryKey>xml</repositoryKey>
            <key>Components_Should_Not_Start_With_New</key>
            <type>CODE_SMELL</type>
            <priority>MAJOR</priority>
            <name>Components Should Not Start With New</name>
            <templateKey>XPathCheck</templateKey>
            <description>Component names must not start with "New " which is Boomi"s default. They should be named to have a accurate description.</description>
            <parameters>
                <parameter>
                    <key>filePattern</key>
                    <value>**/**.xml</value>
                </parameter>
                <parameter>
                    <key>expression</key>
                    <value>/bns:Component/@name[starts-with(., 'New ')]</value>
                </parameter>
                <parameter>
                    <key>message</key>
                    <value>Component names should not begin with *New *. Please rename to match CHG naming standard.</value>
                </parameter>
            </parameters>
        </rule>
        <rule>
            <repositoryKey>xml</repositoryKey>
            <key>Description_Must_Not_Be_Empty</key>
            <type>CODE_SMELL</type>
            <priority>MINOR</priority>
            <name>Description Should Not Be Empty</name>
            <templateKey>XPathCheck</templateKey>
            <description>Process description should be set</description>
            <parameters>
                <parameter>
                    <key>filePattern</key>
                    <value>**/**.xml</value>
                </parameter>
                <parameter>
                    <key>expression</key>
                    <value>/bns:Component[@type='process']/bns:description[not(text())]</value>
                </parameter>
                <parameter>
                    <key>message</key>
                    <value>Process description is not set</value>
                </parameter>
            </parameters>
        </rule>
        <rule>
            <repositoryKey>xml</repositoryKey>
            <key>Exceptions_Must_Have_Params</key>
            <type>CODE_SMELL</type>
            <priority>MAJOR</priority>
            <name>Exceptions must Have Params</name>
            <templateKey>XPathCheck</templateKey>
            <description>Business exception messages must have parameters defined {1} defined</description>
            <parameters>
                <parameter>
                    <key>filePattern</key>
                    <value>**/**.xml</value>
                </parameter>
                <parameter>
                    <key>expression</key>
                    <value>
                        /bns:Component/bns:object/process/shapes/shape[@shapetpye='exception']/configuration/exception/exMessage/text()[not(contains(.,'{1}'))]
                    </value>
                </parameter>
                <parameter>
                    <key>message</key>
                    <value>Business exception message does not have parameters defined.</value>
                </parameter>
            </parameters>
        </rule>
        <rule>
            <repositoryKey>xml</repositoryKey>
            <key>Parameterize_Business_Rules_Error_Messages</key>
            <type>CODE_SMELL</type>
            <priority>MAJOR</priority>
            <name>Business_Rules error messages must be parameterized</name>
            <templateKey>XPathCheck</templateKey>
            <description>Businessrules error messages must have custom parameterized in the error messages</description>
            <parameters>
                <parameter>
                    <key>filePattern</key>
                    <value>**/**.xml</value>
                </parameter>
                <parameter>
                    <key>expression</key>
                    <value>
                        /bns:Component/bns:object/process/shapes/shape[@shapetype='businessrules']/configuration/businessrules/rule/errorMessage/@content[not(contains(.,'{1}'))]
                    </value>
                </parameter>
                <parameter>
                    <key>message</key>
                    <value>Business rule error message does not have parameters defined.</value>
                </parameter>
            </parameters>
        </rule>
        <rule>
            <repositoryKey>xml</repositoryKey>
            <key>Password_must_be_extensible</key>
            <type>BUG</type>
            <priority>MAJOR</priority>
            <name>Password must be extensible</name>
            <templateKey>XPathCheck</templateKey>
            <description>Is the password hard coded? The connection property password must be marked as extensible.</description>
            <parameters>
                <parameter>
                    <key>filePattern</key>
                    <value>**/**.xml</value>
                </parameter>
                <parameter>
                    <key>expression</key>
                    <value>
                        /bns:Component/*/Overrides/Connections/ConnectionOverride/field[@id='password'][@overrideable='false']
                    </value>
                </parameter>
                <parameter>
                    <key>message</key>
                    <value>Connection property "password" must be extensible. @overrideable must be "true"</value>
                </parameter>
            </parameters>
        </rule>
        <rule>
            <repositoryKey>xml</repositoryKey>
            <key>URL_Must_be_Extensible</key>
            <type>BUG</type>
            <priority>MAJOR</priority>
            <name>URL must be extensible</name>
            <templateKey>XPathCheck</templateKey>
            <description>Is the URL hardcoded? URL property used in connection must be marked as extensible.</description>
            <parameters>
                <parameter>
                    <key>filePattern</key>
                    <value>**/**.xml</value>
                </parameter>
                <parameter>
                    <key>expression</key>
                    <value>
                        /bns:Component/*/Overrides/Connections/ConnectionOverride/field[@id='url'][@overrideable='false']
                    </value>
                </parameter>
                <parameter>
                    <key>message</key>
                    <value>Connection property "URL" must be extensible. @overrideable must be "true"</value>
                </parameter>
            </parameters>
        </rule>
        <rule>
            <repositoryKey>xml</repositoryKey>
            <key>User_name_must_be_extensible</key>
            <type>BUG</type>
            <priority>MAJOR</priority>
            <name>User name must be extensible</name>
            <templateKey>XPathCheck</templateKey>
            <description>Is user name hard coded? Connection setting username must be marked as extensible.</description>
            <parameters>
                <parameter>
                    <key>filePattern</key>
                    <value>**/**.xml</value>
                </parameter>
                <parameter>
                    <key>expression</key>
                    <value>
                        /bns:Component/*/Overrides/Connections/ConnectionOverride/field[@id='user'][@overrideable='false']
                    </value>
                </parameter>
                <parameter>
                    <key>message</key>
                    <value>Connection property "user" must be extensible. @overrideable must be "true"</value>
                </parameter>
            </parameters>
        </rule>
        <rule>
            <repositoryKey>xml</repositoryKey>
            <key>AtomQueue_Has_NoDLQ</key>
            <type>BUG</type>
            <priority>MINOR</priority>
            <name>AtomQ Dead Letter Queue</name>
            <templateKey>XPathCheck</templateKey>
            <description>AtomQ does not have a Dead Letter Queue</description>
            <parameters>
                <parameter>
                    <key>filePattern</key>
                    <value>**/**.xml</value>
                </parameter>
                <parameter>
                    <key>expression</key>
                    <value>/bns:Component/bns:object/Operation/Configuration/QueueGetAction[@deadLetterQueue='false']
                    </value>
                </parameter>
                <parameter>
                    <key>message</key>
                    <value>AtomQ Listener should have a Dead Letter Queue</value>
                </parameter>
            </parameters>
        </rule>
        <rule>
            <repositoryKey>xml</repositoryKey>
            <key>General_Mode_Listener</key>
            <type>BUG</type>
            <priority>MINOR</priority>
            <name>General Model Listener Process</name>
            <templateKey>XPathCheck</templateKey>
            <description>A listener Process can run in Low Latency mode instead of General Mode</description>
            <parameters>
                <parameter>
                    <key>filePattern</key>
                    <value>**/**.xml</value>
                </parameter>
                <parameter>
                    <key>expression</key>
                    <value>
                        /bns:Component/bns:object/process/shapes/shape/configuration/connectoraction[@actionType='Listen']/../../../../../process[@workload='general']
                    </value>
                </parameter>
                <parameter>
                    <key>message</key>
                    <value>Process with a Listener start shape is running can run in Low Latency Mode</value>
                </parameter>
            </parameters>
        </rule>
        <rule>
            <repositoryKey>xml</repositoryKey>
            <key>Connection_Name_Standard</key>
            <type>CODE_SMELL</type>
            <priority>MINOR</priority>
            <name>Connection Name Must Follow CHG Standard</name>
            <templateKey>XPathCheck</templateKey>
            <description>The name of connection components must include square brackets ([]) with uppercase text inside (e.g., [Salesforce], [Leads], [SAP]). This rule ensures compliance with CHG naming conventions.</description>
            <parameters>
                <parameter>
                    <key>filePattern</key>
                    <value>**/**.xml</value>
                </parameter>
                <parameter>
                    <key>expression</key>
                    <value>/bns:Component[@type='connector-settings' and not(contains(@name, '[') and contains(@name, ']') and translate(substring-before(substring-after(@name, '['), ']'), 'abcdefghijklmnopqrstuvwxyz', 'ABCDEFGHIJKLMNOPQRSTUVWXYZ') = substring-before(substring-after(@name, '['), ']'))]</value>
                </parameter>
                <parameter>
                    <key>message</key>
                    <value>Connection names must include uppercase text in square brackets (e.g., [Salesforce], [Leads], [SAP]).</value>
                </parameter>
            </parameters>
        </rule>
        <rule>
            <repositoryKey>xml</repositoryKey>
            <key>Connection_Operation_NameStandard</key>
            <type>CODE_SMELL</type>
            <priority>MINOR</priority>
            <name>Connection Operation Name Must Follow CHG Standard</name>
            <templateKey>XPathCheck</templateKey>
            <description>The name of connection operation must include square brackets ([]) with uppercase text inside (e.g., [Salesforce], [Leads], [SAP]). This rule ensures compliance with CHG naming conventions.</description>
            <parameters>
                <parameter>
                    <key>filePattern</key>
                    <value>**/**.xml</value>
                </parameter>
                <parameter>
                    <key>expression</key>
                    <value>/bns:Component[@type='connector-action' and not(contains(@name, '[') and contains(@name, ']') and translate(substring-before(substring-after(@name, '['), ']'), 'abcdefghijklmnopqrstuvwxyz', 'ABCDEFGHIJKLMNOPQRSTUVWXYZ') = substring-before(substring-after(@name, '['), ']'))]</value>
                </parameter>
                <parameter>
                    <key>message</key>
                    <value>Connection operations must include uppercase text in square brackets (e.g., [Salesforce], [Leads], [SAP]).</value>
                </parameter>
            </parameters>
        </rule>
        <rule>
            <repositoryKey>xml</repositoryKey>
            <key>DB_Profile_Name_Format</key>
            <type>CODE_SMELL</type>
            <priority>MAJOR</priority>
            <name>Database Profile name must follow a specific pattern</name>
            <templateKey>XPathCheck</templateKey>
            <description>Database Profile names must start with a tool name inside square brackets (e.g., [SAP], [FOX], [Leads]).</description>
            <parameters>
                <parameter>
                    <key>filePattern</key>
                    <value>**/*.xml</value>
                </parameter>
                <parameter>
                    <key>expression</key>
                    <value>/bns:Component[@type='profile.db' and not(starts-with(@name, '[') and contains(@name, ']'))]</value>
                </parameter>
                <parameter>
                    <key>message</key>
                    <value>Database Profile name must start with a tool name inside square brackets (e.g., [SAP], [FOX], [Leads]).</value>
                </parameter>
            </parameters>
        </rule>
        <rule>
            <repositoryKey>xml</repositoryKey>
            <key>EDI_Profile_Name_Format</key>
            <type>CODE_SMELL</type>
            <priority>MAJOR</priority>
            <name>EDI Profile name must follow a specific pattern</name>
            <templateKey>XPathCheck</templateKey>
            <description>EDI Profile names must start with a tool name inside square brackets (e.g., [SAP], [FOX], [Leads]).</description>
            <parameters>
                <parameter>
                    <key>filePattern</key>
                    <value>**/*.xml</value>
                </parameter>
                <parameter>
                    <key>expression</key>
                    <value>/bns:Component[@type='profile.edi' and not(starts-with(@name, '[') and contains(@name, ']'))]</value>
                </parameter>
                <parameter>
                    <key>message</key>
                    <value>EDI Profile name must start with a tool name inside square brackets (e.g., [SAP], [FOX], [Leads]).</value>
                </parameter>
            </parameters>
        </rule>
        <rule>
            <repositoryKey>xml</repositoryKey>
            <key>FlatFile_Profile_Name_Format</key>
            <type>CODE_SMELL</type>
            <priority>MAJOR</priority>
            <name>Flat File Profile name must follow a specific pattern</name>
            <templateKey>XPathCheck</templateKey>
            <description>Flat File Profile names must start with a tool name inside square brackets (e.g., [SAP], [FOX], [Leads]).</description>
            <parameters>
                <parameter>
                    <key>filePattern</key>
                    <value>**/*.xml</value>
                </parameter>
                <parameter>
                    <key>expression</key>
                    <value>/bns:Component[@type='profile.flatfile' and not(starts-with(@name, '[') and contains(@name, ']'))]</value>
                </parameter>
                <parameter>
                    <key>message</key>
                    <value>Flat File Profile name must start with a tool name inside square brackets (e.g., [SAP], [FOX], [Leads]).</value>
                </parameter>
            </parameters>
        </rule>
        <rule>
            <repositoryKey>xml</repositoryKey>
            <key>JSON_Profile_Name_Format</key>
            <type>CODE_SMELL</type>
            <priority>MAJOR</priority>
            <name>JSON Profile name must follow a specific pattern</name>
            <templateKey>XPathCheck</templateKey>
            <description>JSON Profile names must start with a tool name inside square brackets (e.g., [SAP], [FOX], [Leads]).</description>
            <parameters>
                <parameter>
                    <key>filePattern</key>
                    <value>**/*.xml</value>
                </parameter>
                <parameter>
                    <key>expression</key>
                    <value>/bns:Component[@type='profile.json' and not(starts-with(@name, '[') and contains(@name, ']'))]</value>
                </parameter>
                <parameter>
                    <key>message</key>
                    <value>JSON Profile name must start with a tool name inside square brackets (e.g., [SAP], [FOX], [Leads]).</value>
                </parameter>
            </parameters>
        </rule>
        <rule>
            <repositoryKey>xml</repositoryKey>
            <key>XML_Profile_Name_Format</key>
            <type>CODE_SMELL</type>
            <priority>MAJOR</priority>
            <name>XML Profile name must follow a specific pattern</name>
            <templateKey>XPathCheck</templateKey>
            <description>XML Profile names must start with a tool name inside square brackets (e.g., [SAP], [FOX], [Leads]).</description>
            <parameters>
                <parameter>
                    <key>filePattern</key>
                    <value>**/*.xml</value>
                </parameter>
                <parameter>
                    <key>expression</key>
                    <value>/bns:Component[@type='profile.xml' and not(starts-with(@name, '[') and contains(@name, ']'))]</value>
                </parameter>
                <parameter>
                    <key>message</key>
                    <value>XML Profile name must start with a tool name inside square brackets (e.g., [SAP], [FOX], [Leads]).</value>
                </parameter>
            </parameters>
        </rule>
        <rule>
            <repositoryKey>xml</repositoryKey>
            <key>DocumentPropertyMustHaveSourceValues</key>
            <type>CODE_SMELL</type>
            <priority>MAJOR</priority>
            <name>Document Property Must Have Source Values</name>
            <templateKey>XPathCheck</templateKey>
            <description>Every document property must have at least one source value defined.</description>
            <parameters>
                <parameter>
                    <key>filePattern</key>
                    <value>**/**.xml</value>
                </parameter>
                <parameter>
                    <key>expression</key>
                    <value>
                        /bns:Component/bns:object/process/shapes/shape[@shapetype='documentproperties']/configuration/documentproperties/documentproperty[not(sourcevalues)]
                    </value>
                </parameter>
                <parameter>
                    <key>message</key>
                    <value>Document property "{{@name}}" must have at least one source value defined.</value>
                </parameter>
            </parameters>
        </rule>
        <rule>
            <repositoryKey>xml</repositoryKey>
            <key>ProcessNameFormat</key>
            <type>CODE_SMELL</type>
            <priority>MAJOR</priority>
            <name>Process name must follow CHG pattern standards</name>
            <templateKey>XPathCheck</templateKey>
            <description>Process names should start with either [Listener], [Main], or [Sub], and end with a version number (e.g., -v1).</description>
            <parameters>
                <parameter>
                    <key>filePattern</key>
                    <value>**/*.xml</value>
                </parameter>
                <parameter>
                    <key>expression</key>
                    <value>/bns:Component[@type='process' and not(contains(@name, '[') and contains(@name, ']') and (starts-with(substring-before(substring-after(@name, '['), ']'), 'Listener') or starts-with(substring-before(substring-after(@name, '['), ']'), 'Main') or starts-with(substring-before(substring-after(@name, '['), ']'), 'Sub')) and contains(@name, '-v'))]</value>
                </parameter>
                <parameter>
                    <key>message</key>
                    <value>Process name does not follow the required format defined for CHG.</value>
                </parameter>
            </parameters>
        </rule>
        <rule>
            <repositoryKey>xml</repositoryKey>
            <key>TestProcessNameFormat</key>
            <type>CODE_SMELL</type>
            <priority>MAJOR</priority>
            <name>Test process name must follow CHG pattern standards</name>
            <templateKey>XPathCheck</templateKey>
            <description>Test process names should start with {CT}, {UT}, {IT}, {E2E}, {PT}, or {TS}.</description>
            <parameters>
                <parameter>
                    <key>filePattern</key>
                    <value>**/Test/**/*.xml</value>
                </parameter>
                <parameter>
                    <key>expression</key>
                    <value>/bns:Component[@type='process' and starts-with(@name, '{CT}') or starts-with(@name, '{UT}') or starts-with(@name, '{IT}') or starts-with(@name, '{E2E}') or starts-with(@name, '{PT}') or starts-with(@name, '{TS}')] </value>
                </parameter>
                <parameter>
                    <key>message</key>
                    <value>Test process name must start with {CT}, {UT}, {IT}, {E2E}, {PT}, or {TS}.</value>
                </parameter>
            </parameters>
        </rule>
    </rules>
</profile>
